<?xml version="1.0" encoding="UTF-8"?>
<!--GEDI is developed at Language and Media Processing Laboratory, University of Maryland.-->
<GEDI xmlns="http://lamp.cfar.umd.edu/GEDI" version="1.0">
	<DL_DOCUMENT src="jzx41a00.tif" NrOfPages="1" docTag="xml">
		<DL_PAGE gedi_type="DL_PAGE" src="jzx41a00.tif" pageID="1" width="1200" height="1575">
			<DL_ZONE gedi_type="DLSignature" id="None" col="605" row="930" width="375" height="150" Overlapped="Yes" AuthorID="Newmark, G.B."> </DL_ZONE>
			<DL_ZONE gedi_type="DLLogo" id="None" col="105" row="42" width="189" height="181"> </DL_ZONE>
		</DL_PAGE>
	</DL_DOCUMENT>
</GEDI>